dockertk/__init__.py
dockertk/core/__init__.py
dockertk/core/env_dict.py
dockertk/core/env_lines.py
dockertk/core/env_src.py
dockertk/objects/__init__.py
dockertk/utils/__init__.py
dockertk/utils/dict_utils.py
dockertk/utils/path_utils.py
dockertk/utils/string_utils.py
dockertk-1.0.25.dist-info/WHEEL
dockertk-1.0.25.dist-info/METADATA
dockertk-1.0.25.dist-info/RECORD
