Metadata-Version: 2.1
Name: dockertk
Version: 1.0.25
Summary: 
License: MIT
Author: wayfaring-stranger
Author-email: zw6p226m@duck.com
Requires-Python: >=3.8,<4.0
Classifier: License :: OSI Approved :: MIT License
Classifier: Programming Language :: Python :: 3
Classifier: Programming Language :: Python :: 3.8
Classifier: Programming Language :: Python :: 3.9
Classifier: Programming Language :: Python :: 3.10
Classifier: Programming Language :: Python :: 3.11
Requires-Dist: pytest (>=6.1,<7.0)
